setup.py
yaojiawei20161104/__init__.py
yaojiawei20161104/zz.py
yaojiawei20161104.egg-info/PKG-INFO
yaojiawei20161104.egg-info/SOURCES.txt
yaojiawei20161104.egg-info/dependency_links.txt
yaojiawei20161104.egg-info/entry_points.txt
yaojiawei20161104.egg-info/not-zip-safe
yaojiawei20161104.egg-info/top_level.txt
yaojiawei20161104/skels/__init__.py
yaojiawei20161104/skels/yaojiawei.py