Metadata-Version: 1.0
Name: yaojiawei20161104
Version: 0.1.4
Summary: WSGI HTTP Server for UNIX
Home-page: http://gunicorn.org
Author: Benoit Chesneau
Author-email: benoitc@e-engura.com
License: MIT
Platform: UNKNOWN
